GrizzlySMS/__init__.py
GrizzlySMS/errors.py
GrizzlySMS/grizzly.py
grizzlysms-0.0.2.dist-info/licenses/LICENSE
grizzlysms-0.0.2.dist-info/WHEEL
grizzlysms-0.0.2.dist-info/METADATA
grizzlysms-0.0.2.dist-info/RECORD
