Metadata-Version: 2.4
Name: GrizzlySMS
Version: 0.0.2
Summary: from GrizzlySMS-API import GrizzlySMS
Author-email: AYMEN|d9c <aymenmw@proton.me>
License-Expression: MIT
License-File: LICENSE
